{"end":1000,"w":1024,"h":768,"fps":10,"f":[[{"d":6,"i":0,"e":137}]],"d":["x","x","x","x","x","x",{"l":[{"s":{"x":417,"y":198},"e":{"x":417,"y":197}},{"s":{"x":417,"y":197},"e":{"x":420,"y":195}},{"s":{"x":420,"y":195},"e":{"x":425,"y":191}},{"s":{"x":425,"y":191},"e":{"x":431,"y":188}},{"s":{"x":431,"y":188},"e":{"x":436,"y":185}},{"s":{"x":436,"y":185},"e":{"x":440,"y":184}},{"s":{"x":440,"y":184},"e":{"x":443,"y":183}},{"s":{"x":443,"y":183},"e":{"x":450,"y":180}},{"s":{"x":450,"y":180},"e":{"x":455,"y":177}},{"s":{"x":455,"y":177},"e":{"x":456,"y":175}},{"s":{"x":456,"y":175},"e":{"x":457,"y":173}},{"s":{"x":457,"y":173},"e":{"x":457,"y":171}},{"s":{"x":457,"y":171},"e":{"x":457,"y":169}},{"s":{"x":457,"y":169},"e":{"x":457,"y":166}},{"s":{"x":457,"y":166},"e":{"x":455,"y":163}},{"s":{"x":455,"y":163},"e":{"x":453,"y":160}},{"s":{"x":453,"y":160},"e":{"x":450,"y":158}},{"s":{"x":450,"y":158},"e":{"x":446,"y":157}},{"s":{"x":446,"y":157},"e":{"x":442,"y":156}},{"s":{"x":442,"y":156},"e":{"x":439,"y":154}},{"s":{"x":439,"y":154},"e":{"x":437,"y":153}},{"s":{"x":437,"y":153},"e":{"x":435,"y":150}},{"s":{"x":435,"y":150},"e":{"x":432,"y":145}},{"s":{"x":432,"y":145},"e":{"x":431,"y":142}},{"s":{"x":431,"y":142},"e":{"x":430,"y":138}},{"s":{"x":430,"y":138},"e":{"x":428,"y":133}},{"s":{"x":428,"y":133},"e":{"x":426,"y":128}},{"s":{"x":426,"y":128},"e":{"x":424,"y":125}},{"s":{"x":424,"y":125},"e":{"x":422,"y":124}},{"s":{"x":422,"y":124},"e":{"x":418,"y":123}},{"s":{"x":418,"y":123},"e":{"x":414,"y":122}},{"s":{"x":414,"y":122},"e":{"x":409,"y":121}},{"s":{"x":409,"y":121},"e":{"x":406,"y":121}},{"s":{"x":406,"y":121},"e":{"x":404,"y":121}},{"s":{"x":404,"y":121},"e":{"x":402,"y":121}},{"s":{"x":402,"y":121},"e":{"x":400,"y":121}},{"s":{"x":400,"y":121},"e":{"x":397,"y":121}},{"s":{"x":397,"y":121},"e":{"x":394,"y":123}},{"s":{"x":394,"y":123},"e":{"x":392,"y":123}},{"s":{"x":392,"y":123},"e":{"x":390,"y":124}},{"s":{"x":390,"y":124},"e":{"x":388,"y":124}},{"s":{"x":388,"y":124},"e":{"x":384,"y":124}},{"s":{"x":384,"y":124},"e":{"x":381,"y":124}},{"s":{"x":381,"y":124},"e":{"x":376,"y":123}},{"s":{"x":376,"y":123},"e":{"x":372,"y":121}},{"s":{"x":372,"y":121},"e":{"x":365,"y":119}},{"s":{"x":365,"y":119},"e":{"x":359,"y":118}},{"s":{"x":359,"y":118},"e":{"x":351,"y":116}},{"s":{"x":351,"y":116},"e":{"x":346,"y":116}},{"s":{"x":346,"y":116},"e":{"x":340,"y":116}},{"s":{"x":340,"y":116},"e":{"x":336,"y":116}},{"s":{"x":336,"y":116},"e":{"x":329,"y":116}},{"s":{"x":329,"y":116},"e":{"x":322,"y":116}},{"s":{"x":322,"y":116},"e":{"x":314,"y":117}},{"s":{"x":314,"y":117},"e":{"x":310,"y":117}},{"s":{"x":310,"y":117},"e":{"x":304,"y":117}},{"s":{"x":304,"y":117},"e":{"x":296,"y":117}},{"s":{"x":296,"y":117},"e":{"x":289,"y":117}},{"s":{"x":289,"y":117},"e":{"x":283,"y":117}},{"s":{"x":283,"y":117},"e":{"x":276,"y":114}},{"s":{"x":276,"y":114},"e":{"x":271,"y":113}},{"s":{"x":271,"y":113},"e":{"x":265,"y":111}},{"s":{"x":265,"y":111},"e":{"x":258,"y":110}},{"s":{"x":258,"y":110},"e":{"x":253,"y":109}},{"s":{"x":253,"y":109},"e":{"x":250,"y":108}},{"s":{"x":250,"y":108},"e":{"x":246,"y":108}},{"s":{"x":246,"y":108},"e":{"x":242,"y":108}},{"s":{"x":242,"y":108},"e":{"x":230,"y":114}},{"s":{"x":230,"y":114},"e":{"x":223,"y":119}},{"s":{"x":223,"y":119},"e":{"x":221,"y":120}},{"s":{"x":221,"y":120},"e":{"x":216,"y":125}},{"s":{"x":216,"y":125},"e":{"x":204,"y":135}},{"s":{"x":204,"y":135},"e":{"x":197,"y":141}},{"s":{"x":197,"y":141},"e":{"x":194,"y":144}},{"s":{"x":194,"y":144},"e":{"x":191,"y":149}},{"s":{"x":191,"y":149},"e":{"x":188,"y":154}},{"s":{"x":188,"y":154},"e":{"x":188,"y":159}},{"s":{"x":188,"y":159},"e":{"x":188,"y":163}},{"s":{"x":188,"y":163},"e":{"x":188,"y":167}},{"s":{"x":188,"y":167},"e":{"x":190,"y":172}},{"s":{"x":190,"y":172},"e":{"x":192,"y":175}},{"s":{"x":192,"y":175},"e":{"x":195,"y":178}},{"s":{"x":195,"y":178},"e":{"x":200,"y":181}},{"s":{"x":200,"y":181},"e":{"x":205,"y":184}},{"s":{"x":205,"y":184},"e":{"x":210,"y":186}},{"s":{"x":210,"y":186},"e":{"x":218,"y":188}},{"s":{"x":218,"y":188},"e":{"x":229,"y":190}},{"s":{"x":229,"y":190},"e":{"x":238,"y":193}},{"s":{"x":238,"y":193},"e":{"x":244,"y":196}},{"s":{"x":244,"y":196},"e":{"x":249,"y":198}},{"s":{"x":249,"y":198},"e":{"x":255,"y":200}},{"s":{"x":255,"y":200},"e":{"x":260,"y":204}},{"s":{"x":260,"y":204},"e":{"x":262,"y":208}},{"s":{"x":262,"y":208},"e":{"x":263,"y":211}},{"s":{"x":263,"y":211},"e":{"x":264,"y":216}},{"s":{"x":264,"y":216},"e":{"x":263,"y":222}},{"s":{"x":263,"y":222},"e":{"x":261,"y":226}},{"s":{"x":261,"y":226},"e":{"x":261,"y":230}},{"s":{"x":261,"y":230},"e":{"x":260,"y":233}},{"s":{"x":260,"y":233},"e":{"x":260,"y":236}},{"s":{"x":260,"y":236},"e":{"x":260,"y":240}},{"s":{"x":260,"y":240},"e":{"x":263,"y":244}},{"s":{"x":263,"y":244},"e":{"x":265,"y":247}},{"s":{"x":265,"y":247},"e":{"x":268,"y":250}},{"s":{"x":268,"y":250},"e":{"x":270,"y":253}},{"s":{"x":270,"y":253},"e":{"x":272,"y":257}},{"s":{"x":272,"y":257},"e":{"x":273,"y":266}},{"s":{"x":273,"y":266},"e":{"x":272,"y":274}},{"s":{"x":272,"y":274},"e":{"x":270,"y":280}},{"s":{"x":270,"y":280},"e":{"x":270,"y":286}},{"s":{"x":270,"y":286},"e":{"x":270,"y":292}},{"s":{"x":270,"y":292},"e":{"x":271,"y":300}},{"s":{"x":271,"y":300},"e":{"x":274,"y":303}},{"s":{"x":274,"y":303},"e":{"x":278,"y":303}},{"s":{"x":278,"y":303},"e":{"x":285,"y":303}},{"s":{"x":285,"y":303},"e":{"x":293,"y":300}},{"s":{"x":293,"y":300},"e":{"x":301,"y":293}},{"s":{"x":301,"y":293},"e":{"x":309,"y":285}},{"s":{"x":309,"y":285},"e":{"x":316,"y":279}},{"s":{"x":316,"y":279},"e":{"x":324,"y":273}},{"s":{"x":324,"y":273},"e":{"x":334,"y":267}},{"s":{"x":334,"y":267},"e":{"x":343,"y":261}},{"s":{"x":343,"y":261},"e":{"x":354,"y":254}},{"s":{"x":354,"y":254},"e":{"x":361,"y":248}},{"s":{"x":361,"y":248},"e":{"x":368,"y":241}},{"s":{"x":368,"y":241},"e":{"x":374,"y":234}},{"s":{"x":374,"y":234},"e":{"x":380,"y":227}},{"s":{"x":380,"y":227},"e":{"x":387,"y":221}},{"s":{"x":387,"y":221},"e":{"x":393,"y":216}},{"s":{"x":393,"y":216},"e":{"x":395,"y":213}},{"s":{"x":395,"y":213},"e":{"x":401,"y":207}},{"s":{"x":401,"y":207},"e":{"x":406,"y":203}},{"s":{"x":406,"y":203},"e":{"x":409,"y":201}},{"s":{"x":409,"y":201},"e":{"x":412,"y":199}},{"s":{"x":412,"y":199},"e":{"x":416,"y":196}},{"s":{"x":416,"y":196},"e":{"x":418,"y":194}},{"s":{"x":418,"y":194},"e":{"x":418,"y":194}}],"c":"ffffff","n":2,"r":1}]}